[
  {
    "NumeAnaliza": "nr. 18950699/ BC 6702289",
    "CodAnaliza": null,
    "TipAnaliza": "GENERAL",
    "Valoare": "18950699",
    "ValoareNumerica": 18950699.0,
    "UnitatiMasura": "",
    "ValoareNormalaMin": null,
    "ValoareNormalaMax": null,
    "ValoareNormalaText": "",
    "EsteInAfaraLimitelor": false,
    "DirectieAnormal": null,
    "Metoda": null,
    "DataRecoltare": "14.11.2023",
    "Laborator": "Elite Medical",
    "NumarBuletin": "18950699"
  },
  {
    "NumeAnaliza": "Bd. 15 Noiembrie 60, Brasov",
    "CodAnaliza": null,
    "TipAnaliza": "GENERAL",
    "Valoare": "15",
    "ValoareNumerica": 15.0,
    "UnitatiMasura": "s",
    "ValoareNormalaMin": null,
    "ValoareNormalaMax": null,
    "ValoareNormalaText": "",
    "EsteInAfaraLimitelor": false,
    "DirectieAnormal": null,
    "Metoda": null,
    "DataRecoltare": "14.11.2023",
    "Laborator": "Elite Medical",
    "NumarBuletin": "18950699"
  },
  {
    "NumeAnaliza": "SR EN ISO",
    "CodAnaliza": null,
    "TipAnaliza": "GENERAL",
    "Valoare": "15189",
    "ValoareNumerica": 15189.0,
    "UnitatiMasura": "",
    "ValoareNormalaMin": null,
    "ValoareNormalaMax": null,
    "ValoareNormalaText": "",
    "EsteInAfaraLimitelor": false,
    "DirectieAnormal": null,
    "Metoda": null,
    "DataRecoltare": "14.11.2023",
    "Laborator": "Elite Medical",
    "NumarBuletin": "18950699"
  },
  {
    "NumeAnaliza": "LM 1161",
    "CodAnaliza": null,
    "TipAnaliza": "GENERAL",
    "Valoare": "1161",
    "ValoareNumerica": 1161.0,
    "UnitatiMasura": "",
    "ValoareNormalaMin": null,
    "ValoareNormalaMax": null,
    "ValoareNormalaText": "",
    "EsteInAfaraLimitelor": false,
    "DirectieAnormal": null,
    "Metoda": null,
    "DataRecoltare": "14.11.2023",
    "Laborator": "Elite Medical",
    "NumarBuletin": "18950699"
  },
  {
    "NumeAnaliza": "FG-18-01, editia din 01.07.2023",
    "CodAnaliza": null,
    "TipAnaliza": "GENERAL",
    "Valoare": "18",
    "ValoareNumerica": 18.0,
    "UnitatiMasura": "",
    "ValoareNormalaMin": null,
    "ValoareNormalaMax": null,
    "ValoareNormalaText": "",
    "EsteInAfaraLimitelor": false,
    "DirectieAnormal": null,
    "Metoda": null,
    "DataRecoltare": "14.11.2023",
    "Laborator": "Elite Medical",
    "NumarBuletin": "18950699"
  },
  {
    "NumeAnaliza": "Varsta:",
    "CodAnaliza": null,
    "TipAnaliza": "GENERAL",
    "Valoare": "51",
    "ValoareNumerica": 51.0,
    "UnitatiMasura": "s",
    "ValoareNormalaMin": null,
    "ValoareNormalaMax": null,
    "ValoareNormalaText": "",
    "EsteInAfaraLimitelor": false,
    "DirectieAnormal": null,
    "Metoda": null,
    "DataRecoltare": "14.11.2023",
    "Laborator": "Elite Medical",
    "NumarBuletin": "18950699"
  },
  {
    "NumeAnaliza": "Data - ora cerere:",
    "CodAnaliza": null,
    "TipAnaliza": "GENERAL",
    "Valoare": "14.11",
    "ValoareNumerica": 14.11,
    "UnitatiMasura": "",
    "ValoareNormalaMin": null,
    "ValoareNormalaMax": null,
    "ValoareNormalaText": "",
    "EsteInAfaraLimitelor": false,
    "DirectieAnormal": null,
    "Metoda": null,
    "DataRecoltare": "14.11.2023",
    "Laborator": "Elite Medical",
    "NumarBuletin": "18950699"
  },
  {
    "NumeAnaliza": "Data - ora recoltare::",
    "CodAnaliza": null,
    "TipAnaliza": "GENERAL",
    "Valoare": "14.11",
    "ValoareNumerica": 14.11,
    "UnitatiMasura": "",
    "ValoareNormalaMin": null,
    "ValoareNormalaMax": null,
    "ValoareNormalaText": "",
    "EsteInAfaraLimitelor": false,
    "DirectieAnormal": null,
    "Metoda": null,
    "DataRecoltare": "14.11.2023",
    "Laborator": "Elite Medical",
    "NumarBuletin": "18950699"
  },
  {
    "NumeAnaliza": "Eliberat la:",
    "CodAnaliza": null,
    "TipAnaliza": "GENERAL",
    "Valoare": "15.11",
    "ValoareNumerica": 15.11,
    "UnitatiMasura": "",
    "ValoareNormalaMin": null,
    "ValoareNormalaMax": null,
    "ValoareNormalaText": "",
    "EsteInAfaraLimitelor": false,
    "DirectieAnormal": null,
    "Metoda": null,
    "DataRecoltare": "14.11.2023",
    "Laborator": "Elite Medical",
    "NumarBuletin": "18950699"
  },
  {
    "NumeAnaliza": "Adresa: Str. Bd.",
    "CodAnaliza": null,
    "TipAnaliza": "GENERAL",
    "Valoare": "15",
    "ValoareNumerica": 15.0,
    "UnitatiMasura": "s",
    "ValoareNormalaMin": null,
    "ValoareNormalaMax": null,
    "ValoareNormalaText": "",
    "EsteInAfaraLimitelor": false,
    "DirectieAnormal": null,
    "Metoda": null,
    "DataRecoltare": "14.11.2023",
    "Laborator": "Elite Medical",
    "NumarBuletin": "18950699"
  },
  {
    "NumeAnaliza": "[4.44 - 5.61] / mil./µL",
    "CodAnaliza": null,
    "TipAnaliza": "HEMATOLOGIE",
    "Valoare": "4.44",
    "ValoareNumerica": 4.44,
    "UnitatiMasura": "mil./µL",
    "ValoareNormalaMin": 4.44,
    "ValoareNormalaMax": 5.61,
    "ValoareNormalaText": "[4.44 - 5.61]",
    "EsteInAfaraLimitelor": false,
    "DirectieAnormal": null,
    "Metoda": null,
    "DataRecoltare": "14.11.2023",
    "Laborator": "Elite Medical",
    "NumarBuletin": "18950699"
  },
  {
    "NumeAnaliza": "[13.5 - 16.9] / g/dL",
    "CodAnaliza": null,
    "TipAnaliza": "HEMATOLOGIE",
    "Valoare": "13.5",
    "ValoareNumerica": 13.5,
    "UnitatiMasura": "g/dL",
    "ValoareNormalaMin": 13.5,
    "ValoareNormalaMax": 16.9,
    "ValoareNormalaText": "[13.5 - 16.9]",
    "EsteInAfaraLimitelor": false,
    "DirectieAnormal": null,
    "Metoda": null,
    "DataRecoltare": "14.11.2023",
    "Laborator": "Elite Medical",
    "NumarBuletin": "18950699"
  },
  {
    "NumeAnaliza": "[40 - 49.4] / %",
    "CodAnaliza": null,
    "TipAnaliza": "HEMATOLOGIE",
    "Valoare": "40",
    "ValoareNumerica": 40.0,
    "UnitatiMasura": "%",
    "ValoareNormalaMin": 40.0,
    "ValoareNormalaMax": 49.4,
    "ValoareNormalaText": "[40 - 49.4]",
    "EsteInAfaraLimitelor": false,
    "DirectieAnormal": null,
    "Metoda": null,
    "DataRecoltare": "14.11.2023",
    "Laborator": "Elite Medical",
    "NumarBuletin": "18950699"
  },
  {
    "NumeAnaliza": "[81.8 - 95.5] / fL",
    "CodAnaliza": null,
    "TipAnaliza": "HEMATOLOGIE",
    "Valoare": "81.8",
    "ValoareNumerica": 81.8,
    "UnitatiMasura": "fL",
    "ValoareNormalaMin": 81.8,
    "ValoareNormalaMax": 95.5,
    "ValoareNormalaText": "[81.8 - 95.5]",
    "EsteInAfaraLimitelor": false,
    "DirectieAnormal": null,
    "Metoda": null,
    "DataRecoltare": "14.11.2023",
    "Laborator": "Elite Medical",
    "NumarBuletin": "18950699"
  },
  {
    "NumeAnaliza": "[27 - 32.3] / pg",
    "CodAnaliza": null,
    "TipAnaliza": "HEMATOLOGIE",
    "Valoare": "27",
    "ValoareNumerica": 27.0,
    "UnitatiMasura": "pg",
    "ValoareNormalaMin": 27.0,
    "ValoareNormalaMax": 32.3,
    "ValoareNormalaText": "[27 - 32.3]",
    "EsteInAfaraLimitelor": false,
    "DirectieAnormal": null,
    "Metoda": null,
    "DataRecoltare": "14.11.2023",
    "Laborator": "Elite Medical",
    "NumarBuletin": "18950699"
  },
  {
    "NumeAnaliza": "[32.4 - 35] / g/dL",
    "CodAnaliza": null,
    "TipAnaliza": "HEMATOLOGIE",
    "Valoare": "32.4",
    "ValoareNumerica": 32.4,
    "UnitatiMasura": "g/dL",
    "ValoareNormalaMin": 32.4,
    "ValoareNormalaMax": 35.0,
    "ValoareNormalaText": "[32.4 - 35]",
    "EsteInAfaraLimitelor": false,
    "DirectieAnormal": null,
    "Metoda": null,
    "DataRecoltare": "14.11.2023",
    "Laborator": "Elite Medical",
    "NumarBuletin": "18950699"
  },
  {
    "NumeAnaliza": "[11.6 - 14.8] / %",
    "CodAnaliza": null,
    "TipAnaliza": "HEMATOLOGIE",
    "Valoare": "11.6",
    "ValoareNumerica": 11.6,
    "UnitatiMasura": "%",
    "ValoareNormalaMin": 11.6,
    "ValoareNormalaMax": 14.8,
    "ValoareNormalaText": "[11.6 - 14.8]",
    "EsteInAfaraLimitelor": false,
    "DirectieAnormal": null,
    "Metoda": null,
    "DataRecoltare": "14.11.2023",
    "Laborator": "Elite Medical",
    "NumarBuletin": "18950699"
  },
  {
    "NumeAnaliza": "[37 - 54] / fL",
    "CodAnaliza": null,
    "TipAnaliza": "HEMATOLOGIE",
    "Valoare": "37",
    "ValoareNumerica": 37.0,
    "UnitatiMasura": "fL",
    "ValoareNormalaMin": 37.0,
    "ValoareNormalaMax": 54.0,
    "ValoareNormalaText": "[37 - 54]",
    "EsteInAfaraLimitelor": false,
    "DirectieAnormal": null,
    "Metoda": null,
    "DataRecoltare": "14.11.2023",
    "Laborator": "Elite Medical",
    "NumarBuletin": "18950699"
  },
  {
    "NumeAnaliza": "[3.91 - 10.9] / mii/µL",
    "CodAnaliza": null,
    "TipAnaliza": "HEMATOLOGIE",
    "Valoare": "3.91",
    "ValoareNumerica": 3.91,
    "UnitatiMasura": "mii/µL",
    "ValoareNormalaMin": 3.91,
    "ValoareNormalaMax": 10.9,
    "ValoareNormalaText": "[3.91 - 10.9]",
    "EsteInAfaraLimitelor": false,
    "DirectieAnormal": null,
    "Metoda": null,
    "DataRecoltare": "14.11.2023",
    "Laborator": "Elite Medical",
    "NumarBuletin": "18950699"
  },
  {
    "NumeAnaliza": "[41 - 70.7] / %",
    "CodAnaliza": null,
    "TipAnaliza": "HEMATOLOGIE",
    "Valoare": "41",
    "ValoareNumerica": 41.0,
    "UnitatiMasura": "%",
    "ValoareNormalaMin": 41.0,
    "ValoareNormalaMax": 70.7,
    "ValoareNormalaText": "[41 - 70.7]",
    "EsteInAfaraLimitelor": false,
    "DirectieAnormal": null,
    "Metoda": null,
    "DataRecoltare": "14.11.2023",
    "Laborator": "Elite Medical",
    "NumarBuletin": "18950699"
  },
  {
    "NumeAnaliza": "[0.6 - 7.6] / %",
    "CodAnaliza": null,
    "TipAnaliza": "HEMATOLOGIE",
    "Valoare": "0.6",
    "ValoareNumerica": 0.6,
    "UnitatiMasura": "%",
    "ValoareNormalaMin": 0.6,
    "ValoareNormalaMax": 7.6,
    "ValoareNormalaText": "[0.6 - 7.6]",
    "EsteInAfaraLimitelor": false,
    "DirectieAnormal": null,
    "Metoda": null,
    "DataRecoltare": "14.11.2023",
    "Laborator": "Elite Medical",
    "NumarBuletin": "18950699"
  },
  {
    "NumeAnaliza": "[0.1 - 1.2] / %",
    "CodAnaliza": null,
    "TipAnaliza": "HEMATOLOGIE",
    "Valoare": "0.1",
    "ValoareNumerica": 0.1,
    "UnitatiMasura": "%",
    "ValoareNormalaMin": 0.1,
    "ValoareNormalaMax": 1.2,
    "ValoareNormalaText": "[0.1 - 1.2]",
    "EsteInAfaraLimitelor": false,
    "DirectieAnormal": null,
    "Metoda": null,
    "DataRecoltare": "14.11.2023",
    "Laborator": "Elite Medical",
    "NumarBuletin": "18950699"
  },
  {
    "NumeAnaliza": "[19.1 - 47.9] / %",
    "CodAnaliza": null,
    "TipAnaliza": "HEMATOLOGIE",
    "Valoare": "19.1",
    "ValoareNumerica": 19.1,
    "UnitatiMasura": "%",
    "ValoareNormalaMin": 19.1,
    "ValoareNormalaMax": 47.9,
    "ValoareNormalaText": "[19.1 - 47.9]",
    "EsteInAfaraLimitelor": false,
    "DirectieAnormal": null,
    "Metoda": null,
    "DataRecoltare": "14.11.2023",
    "Laborator": "Elite Medical",
    "NumarBuletin": "18950699"
  },
  {
    "NumeAnaliza": "[5.2 - 15.2] / %",
    "CodAnaliza": null,
    "TipAnaliza": "HEMATOLOGIE",
    "Valoare": "5.2",
    "ValoareNumerica": 5.2,
    "UnitatiMasura": "%",
    "ValoareNormalaMin": 5.2,
    "ValoareNormalaMax": 15.2,
    "ValoareNormalaText": "[5.2 - 15.2]",
    "EsteInAfaraLimitelor": false,
    "DirectieAnormal": null,
    "Metoda": null,
    "DataRecoltare": "14.11.2023",
    "Laborator": "Elite Medical",
    "NumarBuletin": "18950699"
  },
  {
    "NumeAnaliza": "[1.8 - 6.98] / mii/µL",
    "CodAnaliza": null,
    "TipAnaliza": "HEMATOLOGIE",
    "Valoare": "1.8",
    "ValoareNumerica": 1.8,
    "UnitatiMasura": "mii/µL",
    "ValoareNormalaMin": 1.8,
    "ValoareNormalaMax": 6.98,
    "ValoareNormalaText": "[1.8 - 6.98]",
    "EsteInAfaraLimitelor": false,
    "DirectieAnormal": null,
    "Metoda": null,
    "DataRecoltare": "14.11.2023",
    "Laborator": "Elite Medical",
    "NumarBuletin": "18950699"
  },
  {
    "NumeAnaliza": "[0.03 - 0.59] / mii/µL",
    "CodAnaliza": null,
    "TipAnaliza": "HEMATOLOGIE",
    "Valoare": "0.03",
    "ValoareNumerica": 0.03,
    "UnitatiMasura": "mii/µL",
    "ValoareNormalaMin": 0.03,
    "ValoareNormalaMax": 0.59,
    "ValoareNormalaText": "[0.03 - 0.59]",
    "EsteInAfaraLimitelor": false,
    "DirectieAnormal": null,
    "Metoda": null,
    "DataRecoltare": "14.11.2023",
    "Laborator": "Elite Medical",
    "NumarBuletin": "18950699"
  },
  {
    "NumeAnaliza": "[0.01 - 0.07] / mii/µL",
    "CodAnaliza": null,
    "TipAnaliza": "HEMATOLOGIE",
    "Valoare": "0.01",
    "ValoareNumerica": 0.01,
    "UnitatiMasura": "mii/µL",
    "ValoareNormalaMin": 0.01,
    "ValoareNormalaMax": 0.07,
    "ValoareNormalaText": "[0.01 - 0.07]",
    "EsteInAfaraLimitelor": false,
    "DirectieAnormal": null,
    "Metoda": null,
    "DataRecoltare": "14.11.2023",
    "Laborator": "Elite Medical",
    "NumarBuletin": "18950699"
  },
  {
    "NumeAnaliza": "[1.26 - 3.35] / mii/µL",
    "CodAnaliza": null,
    "TipAnaliza": "HEMATOLOGIE",
    "Valoare": "1.26",
    "ValoareNumerica": 1.26,
    "UnitatiMasura": "mii/µL",
    "ValoareNormalaMin": 1.26,
    "ValoareNormalaMax": 3.35,
    "ValoareNormalaText": "[1.26 - 3.35]",
    "EsteInAfaraLimitelor": false,
    "DirectieAnormal": null,
    "Metoda": null,
    "DataRecoltare": "14.11.2023",
    "Laborator": "Elite Medical",
    "NumarBuletin": "18950699"
  },
  {
    "NumeAnaliza": "[0.29 - 0.95] / mii/µL",
    "CodAnaliza": null,
    "TipAnaliza": "HEMATOLOGIE",
    "Valoare": "0.29",
    "ValoareNumerica": 0.29,
    "UnitatiMasura": "mii/µL",
    "ValoareNormalaMin": 0.29,
    "ValoareNormalaMax": 0.95,
    "ValoareNormalaText": "[0.29 - 0.95]",
    "EsteInAfaraLimitelor": false,
    "DirectieAnormal": null,
    "Metoda": null,
    "DataRecoltare": "14.11.2023",
    "Laborator": "Elite Medical",
    "NumarBuletin": "18950699"
  },
  {
    "NumeAnaliza": "[150 - 450] / mii/µL",
    "CodAnaliza": null,
    "TipAnaliza": "HEMATOLOGIE",
    "Valoare": "150",
    "ValoareNumerica": 150.0,
    "UnitatiMasura": "mii/µL",
    "ValoareNormalaMin": 150.0,
    "ValoareNormalaMax": 450.0,
    "ValoareNormalaText": "[150 - 450]",
    "EsteInAfaraLimitelor": false,
    "DirectieAnormal": null,
    "Metoda": null,
    "DataRecoltare": "14.11.2023",
    "Laborator": "Elite Medical",
    "NumarBuletin": "18950699"
  },
  {
    "NumeAnaliza": "[0.17 - 0.35] / %",
    "CodAnaliza": null,
    "TipAnaliza": "HEMATOLOGIE",
    "Valoare": "0.17",
    "ValoareNumerica": 0.17,
    "UnitatiMasura": "%",
    "ValoareNormalaMin": 0.17,
    "ValoareNormalaMax": 0.35,
    "ValoareNormalaText": "[0.17 - 0.35]",
    "EsteInAfaraLimitelor": false,
    "DirectieAnormal": null,
    "Metoda": null,
    "DataRecoltare": "14.11.2023",
    "Laborator": "Elite Medical",
    "NumarBuletin": "18950699"
  },
  {
    "NumeAnaliza": "[7.4 - 13] / fL",
    "CodAnaliza": null,
    "TipAnaliza": "HEMATOLOGIE",
    "Valoare": "7.4",
    "ValoareNumerica": 7.4,
    "UnitatiMasura": "fL",
    "ValoareNormalaMin": 7.4,
    "ValoareNormalaMax": 13.0,
    "ValoareNormalaText": "[7.4 - 13]",
    "EsteInAfaraLimitelor": false,
    "DirectieAnormal": null,
    "Metoda": null,
    "DataRecoltare": "14.11.2023",
    "Laborator": "Elite Medical",
    "NumarBuletin": "18950699"
  },
  {
    "NumeAnaliza": "[8 - 16.5] / fL",
    "CodAnaliza": null,
    "TipAnaliza": "HEMATOLOGIE",
    "Valoare": "8",
    "ValoareNumerica": 8.0,
    "UnitatiMasura": "fL",
    "ValoareNormalaMin": 8.0,
    "ValoareNormalaMax": 16.5,
    "ValoareNormalaText": "[8 - 16.5]",
    "EsteInAfaraLimitelor": false,
    "DirectieAnormal": null,
    "Metoda": null,
    "DataRecoltare": "14.11.2023",
    "Laborator": "Elite Medical",
    "NumarBuletin": "18950699"
  },
  {
    "NumeAnaliza": "[2 - 20] / mm/h",
    "CodAnaliza": null,
    "TipAnaliza": "HEMATOLOGIE",
    "Valoare": "2",
    "ValoareNumerica": 2.0,
    "UnitatiMasura": "mm/h",
    "ValoareNormalaMin": 2.0,
    "ValoareNormalaMax": 20.0,
    "ValoareNormalaText": "[2 - 20]",
    "EsteInAfaraLimitelor": false,
    "DirectieAnormal": null,
    "Metoda": null,
    "DataRecoltare": "14.11.2023",
    "Laborator": "Elite Medical",
    "NumarBuletin": "18950699"
  },
  {
    "NumeAnaliza": "Tiparit la:",
    "CodAnaliza": null,
    "TipAnaliza": "HEMATOLOGIE",
    "Valoare": "04.12",
    "ValoareNumerica": 4.12,
    "UnitatiMasura": "",
    "ValoareNormalaMin": null,
    "ValoareNormalaMax": null,
    "ValoareNormalaText": "",
    "EsteInAfaraLimitelor": false,
    "DirectieAnormal": null,
    "Metoda": null,
    "DataRecoltare": "14.11.2023",
    "Laborator": "Elite Medical",
    "NumarBuletin": "18950699"
  },
  {
    "NumeAnaliza": "[60 - 99]",
    "CodAnaliza": null,
    "TipAnaliza": "BIOCHIMIE",
    "Valoare": "60",
    "ValoareNumerica": 60.0,
    "UnitatiMasura": "",
    "ValoareNormalaMin": 60.0,
    "ValoareNormalaMax": 99.0,
    "ValoareNormalaText": "[60 - 99]",
    "EsteInAfaraLimitelor": false,
    "DirectieAnormal": null,
    "Metoda": null,
    "DataRecoltare": "14.11.2023",
    "Laborator": "Elite Medical",
    "NumarBuletin": "18950699"
  },
  {
    "NumeAnaliza": "Normal:",
    "CodAnaliza": null,
    "TipAnaliza": "BIOCHIMIE",
    "Valoare": "74",
    "ValoareNumerica": 74.0,
    "UnitatiMasura": "",
    "ValoareNormalaMin": null,
    "ValoareNormalaMax": null,
    "ValoareNormalaText": "",
    "EsteInAfaraLimitelor": false,
    "DirectieAnormal": null,
    "Metoda": null,
    "DataRecoltare": "14.11.2023",
    "Laborator": "Elite Medical",
    "NumarBuletin": "18950699"
  },
  {
    "NumeAnaliza": "Glicemie bazala modificata:",
    "CodAnaliza": null,
    "TipAnaliza": "BIOCHIMIE",
    "Valoare": "109",
    "ValoareNumerica": 109.0,
    "UnitatiMasura": "",
    "ValoareNormalaMin": null,
    "ValoareNormalaMax": null,
    "ValoareNormalaText": "",
    "EsteInAfaraLimitelor": false,
    "DirectieAnormal": null,
    "Metoda": null,
    "DataRecoltare": "14.11.2023",
    "Laborator": "Elite Medical",
    "NumarBuletin": "18950699"
  },
  {
    "NumeAnaliza": "Diabet zaharat : >",
    "CodAnaliza": null,
    "TipAnaliza": "BIOCHIMIE",
    "Valoare": "126",
    "ValoareNumerica": 126.0,
    "UnitatiMasura": "",
    "ValoareNormalaMin": null,
    "ValoareNormalaMax": null,
    "ValoareNormalaText": "",
    "EsteInAfaraLimitelor": false,
    "DirectieAnormal": null,
    "Metoda": null,
    "DataRecoltare": "14.11.2023",
    "Laborator": "Elite Medical",
    "NumarBuletin": "18950699"
  },
  {
    "NumeAnaliza": "putin 2 valori crescute >",
    "CodAnaliza": null,
    "TipAnaliza": "BIOCHIMIE",
    "Valoare": "126",
    "ValoareNumerica": 126.0,
    "UnitatiMasura": "s",
    "ValoareNormalaMin": null,
    "ValoareNormalaMax": null,
    "ValoareNormalaText": "",
    "EsteInAfaraLimitelor": false,
    "DirectieAnormal": null,
    "Metoda": null,
    "DataRecoltare": "14.11.2023",
    "Laborator": "Elite Medical",
    "NumarBuletin": "18950699"
  },
  {
    "NumeAnaliza": "<34 / UI/mL",
    "CodAnaliza": null,
    "TipAnaliza": "IMUNOLOGIE",
    "Valoare": "34",
    "ValoareNumerica": 34.0,
    "UnitatiMasura": "UI/mL",
    "ValoareNormalaMin": null,
    "ValoareNormalaMax": null,
    "ValoareNormalaText": "",
    "EsteInAfaraLimitelor": false,
    "DirectieAnormal": null,
    "Metoda": null,
    "DataRecoltare": "14.11.2023",
    "Laborator": "Elite Medical",
    "NumarBuletin": "18950699"
  },
  {
    "NumeAnaliza": "[12 - 22]",
    "CodAnaliza": null,
    "TipAnaliza": "IMUNOLOGIE",
    "Valoare": "12",
    "ValoareNumerica": 12.0,
    "UnitatiMasura": "",
    "ValoareNormalaMin": 12.0,
    "ValoareNormalaMax": 22.0,
    "ValoareNormalaText": "[12 - 22]",
    "EsteInAfaraLimitelor": false,
    "DirectieAnormal": null,
    "Metoda": null,
    "DataRecoltare": "14.11.2023",
    "Laborator": "Elite Medical",
    "NumarBuletin": "18950699"
  },
  {
    "NumeAnaliza": "trimestrul I",
    "CodAnaliza": null,
    "TipAnaliza": "IMUNOLOGIE",
    "Valoare": "12.05",
    "ValoareNumerica": 12.05,
    "UnitatiMasura": "pmol/L",
    "ValoareNormalaMin": null,
    "ValoareNormalaMax": null,
    "ValoareNormalaText": "",
    "EsteInAfaraLimitelor": false,
    "DirectieAnormal": null,
    "Metoda": null,
    "DataRecoltare": "14.11.2023",
    "Laborator": "Elite Medical",
    "NumarBuletin": "18950699"
  },
  {
    "NumeAnaliza": "trimestrul II",
    "CodAnaliza": null,
    "TipAnaliza": "IMUNOLOGIE",
    "Valoare": "9.63",
    "ValoareNumerica": 9.63,
    "UnitatiMasura": "pmol/L",
    "ValoareNormalaMin": null,
    "ValoareNormalaMax": null,
    "ValoareNormalaText": "",
    "EsteInAfaraLimitelor": false,
    "DirectieAnormal": null,
    "Metoda": null,
    "DataRecoltare": "14.11.2023",
    "Laborator": "Elite Medical",
    "NumarBuletin": "18950699"
  },
  {
    "NumeAnaliza": "trimestrul III",
    "CodAnaliza": null,
    "TipAnaliza": "IMUNOLOGIE",
    "Valoare": "8.39",
    "ValoareNumerica": 8.39,
    "UnitatiMasura": "pmol/L",
    "ValoareNormalaMin": null,
    "ValoareNormalaMax": null,
    "ValoareNormalaText": "",
    "EsteInAfaraLimitelor": false,
    "DirectieAnormal": null,
    "Metoda": null,
    "DataRecoltare": "14.11.2023",
    "Laborator": "Elite Medical",
    "NumarBuletin": "18950699"
  },
  {
    "NumeAnaliza": "(0.27 - 4.2)",
    "CodAnaliza": null,
    "TipAnaliza": "IMUNOLOGIE",
    "Valoare": "0.27",
    "ValoareNumerica": 0.27,
    "UnitatiMasura": "",
    "ValoareNormalaMin": 27.0,
    "ValoareNormalaMax": 42.0,
    "ValoareNormalaText": "(0.27 - 4.2)",
    "EsteInAfaraLimitelor": true,
    "DirectieAnormal": "LOW",
    "Metoda": null,
    "DataRecoltare": "14.11.2023",
    "Laborator": "Elite Medical",
    "NumarBuletin": "18950699"
  },
  {
    "NumeAnaliza": "Trim I:",
    "CodAnaliza": null,
    "TipAnaliza": "IMUNOLOGIE",
    "Valoare": "0.33",
    "ValoareNumerica": 0.33,
    "UnitatiMasura": "",
    "ValoareNormalaMin": null,
    "ValoareNormalaMax": null,
    "ValoareNormalaText": "",
    "EsteInAfaraLimitelor": false,
    "DirectieAnormal": null,
    "Metoda": null,
    "DataRecoltare": "14.11.2023",
    "Laborator": "Elite Medical",
    "NumarBuletin": "18950699"
  },
  {
    "NumeAnaliza": "Trim II:",
    "CodAnaliza": null,
    "TipAnaliza": "IMUNOLOGIE",
    "Valoare": "0.35",
    "ValoareNumerica": 0.35,
    "UnitatiMasura": "",
    "ValoareNormalaMin": null,
    "ValoareNormalaMax": null,
    "ValoareNormalaText": "",
    "EsteInAfaraLimitelor": false,
    "DirectieAnormal": null,
    "Metoda": null,
    "DataRecoltare": "14.11.2023",
    "Laborator": "Elite Medical",
    "NumarBuletin": "18950699"
  },
  {
    "NumeAnaliza": "Trim III:",
    "CodAnaliza": null,
    "TipAnaliza": "IMUNOLOGIE",
    "Valoare": "0.21",
    "ValoareNumerica": 0.21,
    "UnitatiMasura": "UI/mL",
    "ValoareNormalaMin": null,
    "ValoareNormalaMax": null,
    "ValoareNormalaText": "",
    "EsteInAfaraLimitelor": false,
    "DirectieAnormal": null,
    "Metoda": null,
    "DataRecoltare": "14.11.2023",
    "Laborator": "Elite Medical",
    "NumarBuletin": "18950699"
  },
  {
    "NumeAnaliza": "Datele dumneavoastra personale sunt prelucrate de Poliana in scopul prestarii de servicii medicale. Va puteti exercita drepturile prevazute in Regulamentul nr.",
    "CodAnaliza": null,
    "TipAnaliza": "IMUNOLOGIE",
    "Valoare": "679",
    "ValoareNumerica": 679.0,
    "UnitatiMasura": "s",
    "ValoareNormalaMin": null,
    "ValoareNormalaMax": null,
    "ValoareNormalaText": "",
    "EsteInAfaraLimitelor": false,
    "DirectieAnormal": null,
    "Metoda": null,
    "DataRecoltare": "14.11.2023",
    "Laborator": "Elite Medical",
    "NumarBuletin": "18950699"
  },
  {
    "NumeAnaliza": "2016 al Parlamentului European si al Consiliului Uniunii Europene in conditiile mentionate in Nota de informare cu privire la prelucrarea datelor cu caracter personal,",
    "CodAnaliza": null,
    "TipAnaliza": "IMUNOLOGIE",
    "Valoare": "2016",
    "ValoareNumerica": 2016.0,
    "UnitatiMasura": "s",
    "ValoareNormalaMin": null,
    "ValoareNormalaMax": null,
    "ValoareNormalaText": "",
    "EsteInAfaraLimitelor": false,
    "DirectieAnormal": null,
    "Metoda": null,
    "DataRecoltare": "14.11.2023",
    "Laborator": "Elite Medical",
    "NumarBuletin": "18950699"
  },
  {
    "NumeAnaliza": "Tiparit la:",
    "CodAnaliza": null,
    "TipAnaliza": "IMUNOLOGIE",
    "Valoare": "04.12",
    "ValoareNumerica": 4.12,
    "UnitatiMasura": "",
    "ValoareNormalaMin": null,
    "ValoareNormalaMax": null,
    "ValoareNormalaText": "",
    "EsteInAfaraLimitelor": false,
    "DirectieAnormal": null,
    "Metoda": null,
    "DataRecoltare": "14.11.2023",
    "Laborator": "Elite Medical",
    "NumarBuletin": "18950699"
  },
  {
    "NumeAnaliza": "nr. 18950699/ BC 6702289",
    "CodAnaliza": null,
    "TipAnaliza": "IMUNOLOGIE",
    "Valoare": "18950699",
    "ValoareNumerica": 18950699.0,
    "UnitatiMasura": "",
    "ValoareNormalaMin": null,
    "ValoareNormalaMax": null,
    "ValoareNormalaText": "",
    "EsteInAfaraLimitelor": false,
    "DirectieAnormal": null,
    "Metoda": null,
    "DataRecoltare": "14.11.2023",
    "Laborator": "Elite Medical",
    "NumarBuletin": "18950699"
  },
  {
    "NumeAnaliza": "Calea Dorobantilor 32A, Bucuresti Sectorul",
    "CodAnaliza": null,
    "TipAnaliza": "IMUNOLOGIE",
    "Valoare": "1",
    "ValoareNumerica": 1.0,
    "UnitatiMasura": "s",
    "ValoareNormalaMin": null,
    "ValoareNormalaMax": null,
    "ValoareNormalaText": "",
    "EsteInAfaraLimitelor": false,
    "DirectieAnormal": null,
    "Metoda": null,
    "DataRecoltare": "14.11.2023",
    "Laborator": "Elite Medical",
    "NumarBuletin": "18950699"
  },
  {
    "NumeAnaliza": "FG-18-01, editia din 01.07.2023",
    "CodAnaliza": null,
    "TipAnaliza": "IMUNOLOGIE",
    "Valoare": "18",
    "ValoareNumerica": 18.0,
    "UnitatiMasura": "",
    "ValoareNormalaMin": null,
    "ValoareNormalaMax": null,
    "ValoareNormalaText": "",
    "EsteInAfaraLimitelor": false,
    "DirectieAnormal": null,
    "Metoda": null,
    "DataRecoltare": "14.11.2023",
    "Laborator": "Elite Medical",
    "NumarBuletin": "18950699"
  },
  {
    "NumeAnaliza": "Varsta:",
    "CodAnaliza": null,
    "TipAnaliza": "IMUNOLOGIE",
    "Valoare": "51",
    "ValoareNumerica": 51.0,
    "UnitatiMasura": "s",
    "ValoareNormalaMin": null,
    "ValoareNormalaMax": null,
    "ValoareNormalaText": "",
    "EsteInAfaraLimitelor": false,
    "DirectieAnormal": null,
    "Metoda": null,
    "DataRecoltare": "14.11.2023",
    "Laborator": "Elite Medical",
    "NumarBuletin": "18950699"
  },
  {
    "NumeAnaliza": "Data - ora cerere:",
    "CodAnaliza": null,
    "TipAnaliza": "IMUNOLOGIE",
    "Valoare": "14.11",
    "ValoareNumerica": 14.11,
    "UnitatiMasura": "",
    "ValoareNormalaMin": null,
    "ValoareNormalaMax": null,
    "ValoareNormalaText": "",
    "EsteInAfaraLimitelor": false,
    "DirectieAnormal": null,
    "Metoda": null,
    "DataRecoltare": "14.11.2023",
    "Laborator": "Elite Medical",
    "NumarBuletin": "18950699"
  },
  {
    "NumeAnaliza": "Data - ora recoltare::",
    "CodAnaliza": null,
    "TipAnaliza": "IMUNOLOGIE",
    "Valoare": "14.11",
    "ValoareNumerica": 14.11,
    "UnitatiMasura": "",
    "ValoareNormalaMin": null,
    "ValoareNormalaMax": null,
    "ValoareNormalaText": "",
    "EsteInAfaraLimitelor": false,
    "DirectieAnormal": null,
    "Metoda": null,
    "DataRecoltare": "14.11.2023",
    "Laborator": "Elite Medical",
    "NumarBuletin": "18950699"
  },
  {
    "NumeAnaliza": "Eliberat la:",
    "CodAnaliza": null,
    "TipAnaliza": "IMUNOLOGIE",
    "Valoare": "15.11",
    "ValoareNumerica": 15.11,
    "UnitatiMasura": "",
    "ValoareNormalaMin": null,
    "ValoareNormalaMax": null,
    "ValoareNormalaText": "",
    "EsteInAfaraLimitelor": false,
    "DirectieAnormal": null,
    "Metoda": null,
    "DataRecoltare": "14.11.2023",
    "Laborator": "Elite Medical",
    "NumarBuletin": "18950699"
  },
  {
    "NumeAnaliza": "Adresa: Str. Bd.",
    "CodAnaliza": null,
    "TipAnaliza": "IMUNOLOGIE",
    "Valoare": "15",
    "ValoareNumerica": 15.0,
    "UnitatiMasura": "s",
    "ValoareNormalaMin": null,
    "ValoareNormalaMax": null,
    "ValoareNormalaText": "",
    "EsteInAfaraLimitelor": false,
    "DirectieAnormal": null,
    "Metoda": null,
    "DataRecoltare": "14.11.2023",
    "Laborator": "Elite Medical",
    "NumarBuletin": "18950699"
  },
  {
    "NumeAnaliza": "Datele dumneavoastra personale sunt prelucrate de Poliana in scopul prestarii de servicii medicale. Va puteti exercita drepturile prevazute in Regulamentul nr.",
    "CodAnaliza": null,
    "TipAnaliza": "IMUNOLOGIE",
    "Valoare": "679",
    "ValoareNumerica": 679.0,
    "UnitatiMasura": "s",
    "ValoareNormalaMin": null,
    "ValoareNormalaMax": null,
    "ValoareNormalaText": "",
    "EsteInAfaraLimitelor": false,
    "DirectieAnormal": null,
    "Metoda": null,
    "DataRecoltare": "14.11.2023",
    "Laborator": "Elite Medical",
    "NumarBuletin": "18950699"
  },
  {
    "NumeAnaliza": "2016 al Parlamentului European si al Consiliului Uniunii Europene in conditiile mentionate in Nota de informare cu privire la prelucrarea datelor cu caracter personal,",
    "CodAnaliza": null,
    "TipAnaliza": "IMUNOLOGIE",
    "Valoare": "2016",
    "ValoareNumerica": 2016.0,
    "UnitatiMasura": "s",
    "ValoareNormalaMin": null,
    "ValoareNormalaMax": null,
    "ValoareNormalaText": "",
    "EsteInAfaraLimitelor": false,
    "DirectieAnormal": null,
    "Metoda": null,
    "DataRecoltare": "14.11.2023",
    "Laborator": "Elite Medical",
    "NumarBuletin": "18950699"
  },
  {
    "NumeAnaliza": "Tiparit la:",
    "CodAnaliza": null,
    "TipAnaliza": "IMUNOLOGIE",
    "Valoare": "04.12",
    "ValoareNumerica": 4.12,
    "UnitatiMasura": "",
    "ValoareNormalaMin": null,
    "ValoareNormalaMax": null,
    "ValoareNormalaText": "",
    "EsteInAfaraLimitelor": false,
    "DirectieAnormal": null,
    "Metoda": null,
    "DataRecoltare": "14.11.2023",
    "Laborator": "Elite Medical",
    "NumarBuletin": "18950699"
  }
]